{
  "rojoExplorer.displayName": "Rojo Explorer",
  "rojoExplorer.description": "A VS Code extension that presents a Roblox Studio-like explorer for Rojo workspaces.",
  "rojoExplorer.commands.refresh.title": "Refresh Rojo Explorer",
  "rojoExplorer.commands.openRojoProject.title": "Open Rojo Project",
  "rojoExplorer.commands.openResource.title": "Open Resource",
  "rojoExplorer.commands.selectNode.title": "Select Resource",
  "rojoExplorer.commands.revealInFileExplorer.title": "Reveal in File Explorer",
  "rojoExplorer.commands.revealInVsCodeExplorer.title": "Reveal in VS Code Explorer",
  "rojoExplorer.commands.copyStudioPath.title": "Copy Studio Path",
  "rojoExplorer.commands.copySourcePath.title": "Copy Source Path",
  "rojoExplorer.commands.copyRelativeSourcePath.title": "Copy Relative Source Path",
  "rojoExplorer.commands.createFolder.title": "New Folder",
  "rojoExplorer.commands.createScript.title": "New Script",
  "rojoExplorer.commands.createLocalScript.title": "New LocalScript",
  "rojoExplorer.commands.createModuleScript.title": "New ModuleScript",
  "rojoExplorer.commands.createInitScript.title": "Create Init Script...",
  "rojoExplorer.commands.createInstance.title": "New Instance...",
  "rojoExplorer.commands.createModel.title": "New Model",
  "rojoExplorer.commands.createRemoteEvent.title": "New RemoteEvent",
  "rojoExplorer.commands.createRemoteFunction.title": "New RemoteFunction",
  "rojoExplorer.commands.createBindableEvent.title": "New BindableEvent",
  "rojoExplorer.commands.createBindableFunction.title": "New BindableFunction",
  "rojoExplorer.commands.createStringValue.title": "New StringValue",
  "rojoExplorer.commands.createLocalizationTable.title": "New LocalizationTable",
  "rojoExplorer.commands.createJsonModule.title": "New JSON Module",
  "rojoExplorer.commands.createTomlModule.title": "New TOML Module",
  "rojoExplorer.commands.renameResource.title": "Rename Resource",
  "rojoExplorer.commands.duplicateResource.title": "Duplicate Resource",
  "rojoExplorer.commands.openResourceMeta.title": "Open/Create Meta File",
  "rojoExplorer.commands.openResourceInitMeta.title": "Open/Create Init Meta File",
  "rojoExplorer.commands.moveResource.title": "Move Resource...",
  "rojoExplorer.commands.deleteResource.title": "Delete Resource",
  "rojoExplorer.commands.editProjectMapping.title": "Edit Project Mapping...",
  "rojoExplorer.views.explorer.name": "Rojo Explorer"
}
